[
  {
    "order_id": "ACM-2025-06201",
    "status": "delivered",
    "carrier": "DHL",
    "tracking_number": "DE100000001",
    "delivery_estimate": "Delivered 22 Dec 2025",
    "order_date": "2025-12-18",
    "items": [
      { "sku": "ELEC-AUD-001-BLK", "name": "SoundWave Studio Pro Headphones", "category": "Electronics", "color": "Black", "quantity": 1, "price": 249.00 },
      { "sku": "ELEC-CHR-001", "name": "PowerCore Qi Wireless Charger Pad", "category": "Electronics", "color": "White", "quantity": 1, "price": 29.00 }
    ],
    "total": 278.00,
    "currency": "EUR",
    "eligible_for_return": false,
    "return_deadline": "2026-01-18"
  },
  {
    "order_id": "ACM-2025-06315",
    "status": "delivered",
    "carrier": "DPD",
    "tracking_number": "DPD200000002",
    "delivery_estimate": "Delivered 30 Dec 2025",
    "order_date": "2025-12-27",
    "items": [
      { "sku": "CLTH-TEE-002-WHT-M", "name": "UrbanThread Essential Crew Tee", "category": "Clothing & Apparel", "color": "White", "size": "M", "quantity": 2, "price": 29.00 },
      { "sku": "CLTH-JNS-001-BLU-L", "name": "UrbanThread Slim Straight Jeans", "category": "Clothing & Apparel", "color": "Indigo Blue", "size": "L", "quantity": 1, "price": 79.00 }
    ],
    "total": 137.00,
    "currency": "EUR",
    "eligible_for_return": false,
    "return_deadline": "2026-01-27"
  },
  {
    "order_id": "ACM-2026-00112",
    "status": "delivered",
    "carrier": "UPS",
    "tracking_number": "UPS300000003",
    "delivery_estimate": "Delivered 16 Jan 2026",
    "order_date": "2026-01-12",
    "items": [
      { "sku": "HOME-COF-001", "name": "HomeEssence BrewMaster Drip Coffee Maker", "category": "Home & Kitchen", "color": "Stainless Steel", "quantity": 1, "price": 89.00 },
      { "sku": "HOME-KNF-001", "name": "ChefCraft Pro Knife Set (8-Piece)", "category": "Home & Kitchen", "color": "Silver/Wood", "quantity": 1, "price": 149.00 }
    ],
    "total": 238.00,
    "currency": "EUR",
    "eligible_for_return": false,
    "return_deadline": "2026-02-12"
  },
  {
    "order_id": "ACM-2026-00298",
    "status": "delivered",
    "carrier": "Hermes",
    "tracking_number": "HRM400000004",
    "delivery_estimate": "Delivered 28 Jan 2026",
    "order_date": "2026-01-24",
    "items": [
      { "sku": "SPRT-RSB-001", "name": "PeakForm Resistance Band Set (5-Pack)", "category": "Sports & Fitness", "color": "Multi-Color", "quantity": 1, "price": 24.00 },
      { "sku": "SPRT-YOG-001", "name": "PeakForm EcoGrip Yoga Mat", "category": "Sports & Fitness", "color": "Sage Green", "quantity": 1, "price": 39.00 }
    ],
    "total": 63.00,
    "currency": "EUR",
    "eligible_for_return": false,
    "return_deadline": "2026-02-24"
  },
  {
    "order_id": "ACM-2026-01050",
    "status": "delivered",
    "carrier": "DHL",
    "tracking_number": "DE500000005",
    "delivery_estimate": "Delivered 14 Feb 2026",
    "order_date": "2026-02-10",
    "items": [
      { "sku": "ELEC-PHN-001-BLK", "name": "ProVision Smartphone X1", "category": "Electronics", "color": "Black", "quantity": 1, "price": 799.00 },
      { "sku": "ELEC-AUD-003-WHT", "name": "SoundWave AirPods Wireless Earbuds", "category": "Electronics", "color": "White", "quantity": 1, "price": 149.00 }
    ],
    "total": 948.00,
    "currency": "EUR",
    "eligible_for_return": false,
    "return_deadline": "2026-03-10"
  },
  {
    "order_id": "ACM-2026-01422",
    "status": "cancelled",
    "carrier": null,
    "tracking_number": null,
    "delivery_estimate": "Cancelled by customer",
    "order_date": "2026-02-20",
    "items": [
      { "sku": "ELEC-MON-001", "name": "VisionPro UltraWide Monitor 34\"", "category": "Electronics", "color": "Black", "quantity": 1, "price": 599.00 }
    ],
    "total": 599.00,
    "currency": "EUR",
    "eligible_for_return": false,
    "return_deadline": null
  },
  {
    "order_id": "ACM-2026-01789",
    "status": "delivered",
    "carrier": "DPD",
    "tracking_number": "DPD600000006",
    "delivery_estimate": "Delivered 8 Mar 2026",
    "order_date": "2026-03-04",
    "items": [
      { "sku": "BEAU-MST-001", "name": "GlowLab HydraBoost Moisturizer", "category": "Beauty & Personal Care", "color": "White", "quantity": 1, "price": 32.00 },
      { "sku": "BEAU-SER-001", "name": "GlowLab Vitamin C Brightening Serum", "category": "Beauty & Personal Care", "color": "Amber", "quantity": 1, "price": 38.00 },
      { "sku": "BEAU-SPF-001", "name": "GlowLab ShieldGlow Sunscreen SPF50", "category": "Beauty & Personal Care", "color": "Transparent", "quantity": 1, "price": 28.00 }
    ],
    "total": 98.00,
    "currency": "EUR",
    "eligible_for_return": false,
    "return_deadline": "2026-04-04"
  },
  {
    "order_id": "ACM-2026-02100",
    "status": "delivered",
    "carrier": "DHL",
    "tracking_number": "DE700000007",
    "delivery_estimate": "Delivered 18 Mar 2026",
    "order_date": "2026-03-15",
    "items": [
      { "sku": "BOOK-SCI-001", "name": "The Last Signal — A Novel", "category": "Books & Media", "color": "N/A", "quantity": 1, "price": 16.00 },
      { "sku": "BOOK-CKB-001", "name": "The Mediterranean Table: 120 Recipes", "category": "Books & Media", "color": "N/A", "quantity": 1, "price": 35.00 },
      { "sku": "BOOK-JRN-001", "name": "Mindful Moments Dotted Journal", "category": "Books & Media", "color": "Forest Green", "quantity": 1, "price": 19.00 }
    ],
    "total": 70.00,
    "currency": "EUR",
    "eligible_for_return": false,
    "return_deadline": "2026-04-15"
  },
  {
    "order_id": "ACM-2026-02455",
    "status": "returned",
    "carrier": "DHL",
    "tracking_number": "DE800000008",
    "delivery_estimate": "Returned — refund processed",
    "order_date": "2026-03-28",
    "items": [
      { "sku": "CLTH-SNK-001-WHT-42", "name": "StrideCraft CloudWalk Sneakers", "category": "Clothing & Apparel", "color": "White", "size": "42", "quantity": 1, "price": 99.00 }
    ],
    "total": 99.00,
    "currency": "EUR",
    "eligible_for_return": false,
    "return_deadline": null
  },
  {
    "order_id": "ACM-2026-02800",
    "status": "delivered",
    "carrier": "UPS",
    "tracking_number": "UPS900000009",
    "delivery_estimate": "Delivered 12 Apr 2026",
    "order_date": "2026-04-08",
    "items": [
      { "sku": "TOYS-STR-001", "name": "FunFactory Realm of Conquest Strategy Game", "category": "Toys & Games", "color": "Multi-Color", "quantity": 1, "price": 54.00 },
      { "sku": "TOYS-PZL-001", "name": "BrainBox 1000-Piece World Wonders Puzzle", "category": "Toys & Games", "color": "Multi-Color", "quantity": 1, "price": 22.00 },
      { "sku": "TOYS-SPD-001", "name": "BrainBox SpeedCube 3x3", "category": "Toys & Games", "color": "Stickerless Multi", "quantity": 1, "price": 14.00 }
    ],
    "total": 90.00,
    "currency": "EUR",
    "eligible_for_return": false,
    "return_deadline": "2026-05-08"
  },
  {
    "order_id": "ACM-2026-03150",
    "status": "delivered",
    "carrier": "DPD",
    "tracking_number": "DPD101000010",
    "delivery_estimate": "Delivered 22 Apr 2026",
    "order_date": "2026-04-18",
    "items": [
      { "sku": "GRDN-GRL-001", "name": "GrillMaster Classic Charcoal Grill", "category": "Garden & Outdoor", "color": "Black", "quantity": 1, "price": 179.00 },
      { "sku": "GRDN-CLR-001", "name": "GrillMaster IceBox 52L Cooler", "category": "Garden & Outdoor", "color": "Desert Tan", "quantity": 1, "price": 199.00 }
    ],
    "total": 378.00,
    "currency": "EUR",
    "eligible_for_return": true,
    "return_deadline": "2026-05-18"
  },
  {
    "order_id": "ACM-2026-03500",
    "status": "delivered",
    "carrier": "Hermes",
    "tracking_number": "HRM110000011",
    "delivery_estimate": "Delivered 2 May 2026",
    "order_date": "2026-04-29",
    "items": [
      { "sku": "SPRT-FMR-001", "name": "PeakForm Textured Foam Roller 45cm", "category": "Sports & Fitness", "color": "Blue", "quantity": 1, "price": 22.00 },
      { "sku": "SPRT-WTR-001", "name": "PeakForm HydroFlask Insulated Bottle 750ml", "category": "Sports & Fitness", "color": "Pacific Blue", "quantity": 1, "price": 29.00 },
      { "sku": "SPRT-JMP-001", "name": "PeakForm Speed Jump Rope", "category": "Sports & Fitness", "color": "Black", "quantity": 1, "price": 15.00 }
    ],
    "total": 66.00,
    "currency": "EUR",
    "eligible_for_return": true,
    "return_deadline": "2026-05-29"
  },
  {
    "order_id": "ACM-2026-03890",
    "status": "delivered",
    "carrier": "DHL",
    "tracking_number": "DE120000012",
    "delivery_estimate": "Delivered 10 May 2026",
    "order_date": "2026-05-06",
    "items": [
      { "sku": "HOME-BLK-001", "name": "CozyNest Sherpa Throw Blanket", "category": "Home & Kitchen", "color": "Charcoal Gray", "quantity": 1, "price": 49.00 },
      { "sku": "HOME-CND-001", "name": "CozyNest Soy Wax Scented Candle", "category": "Home & Kitchen", "color": "Amber", "quantity": 2, "price": 24.00 }
    ],
    "total": 97.00,
    "currency": "EUR",
    "eligible_for_return": true,
    "return_deadline": "2026-06-06"
  },
  {
    "order_id": "ACM-2026-04120",
    "status": "shipped",
    "carrier": "DHL",
    "tracking_number": "DE130000013",
    "delivery_estimate": "Arriving tomorrow",
    "order_date": "2026-05-15",
    "items": [
      { "sku": "ELEC-WCH-001-BLK", "name": "VisionPro FitWatch Ultra", "category": "Electronics", "color": "Black", "quantity": 1, "price": 349.00 }
    ],
    "total": 349.00,
    "currency": "EUR",
    "eligible_for_return": false,
    "return_deadline": null
  },
  {
    "order_id": "ACM-2026-04350",
    "status": "processing",
    "carrier": null,
    "tracking_number": null,
    "delivery_estimate": "Estimated dispatch in 1 business day",
    "order_date": "2026-05-19",
    "items": [
      { "sku": "GRDN-HMK-001", "name": "TerraCraft Brazilian Cotton Hammock", "category": "Garden & Outdoor", "color": "Natural/Stripe", "quantity": 1, "price": 99.00 },
      { "sku": "GRDN-SLR-001", "name": "GreenThumb Solar Path Lights (6-Pack)", "category": "Garden & Outdoor", "color": "Stainless Steel", "quantity": 1, "price": 34.00 }
    ],
    "total": 133.00,
    "currency": "EUR",
    "eligible_for_return": false,
    "return_deadline": null
  },
  {
    "order_id": "ACM-2026-04500",
    "status": "processing",
    "carrier": null,
    "tracking_number": null,
    "delivery_estimate": "Estimated dispatch in 2 business days",
    "order_date": "2026-05-22",
    "items": [
      { "sku": "CLTH-HOD-001-GRY-L", "name": "UrbanThread Pullover Hoodie", "category": "Clothing & Apparel", "color": "Heather Gray", "size": "L", "quantity": 1, "price": 59.00 },
      { "sku": "CLTH-BMB-001-BLK-M", "name": "UrbanThread Bomber Jacket", "category": "Clothing & Apparel", "color": "Black", "size": "M", "quantity": 1, "price": 129.00 }
    ],
    "total": 188.00,
    "currency": "EUR",
    "eligible_for_return": false,
    "return_deadline": null
  },
  {
    "order_id": "ACM-2026-04610",
    "status": "cancelled",
    "carrier": null,
    "tracking_number": null,
    "delivery_estimate": "Cancelled — item out of stock",
    "order_date": "2026-05-10",
    "items": [
      { "sku": "ELEC-LPT-001-SLV", "name": "TechNova UltraBook Pro 15", "category": "Electronics", "color": "Silver", "quantity": 1, "price": 1299.00 }
    ],
    "total": 1299.00,
    "currency": "EUR",
    "eligible_for_return": false,
    "return_deadline": null
  },
  {
    "order_id": "ACM-2026-03000",
    "status": "delivered",
    "carrier": "DHL",
    "tracking_number": "DE140000014",
    "delivery_estimate": "Delivered 15 Apr 2026",
    "order_date": "2026-04-11",
    "items": [
      { "sku": "BEAU-CLG-001", "name": "PureScent Oakmoss & Bergamot Cologne", "category": "Beauty & Personal Care", "color": "Clear/Amber", "quantity": 1, "price": 79.00 },
      { "sku": "BEAU-HDR-001", "name": "VelvetTouch IonPro Hair Dryer", "category": "Beauty & Personal Care", "color": "Rose Gold", "quantity": 1, "price": 69.00 }
    ],
    "total": 148.00,
    "currency": "EUR",
    "eligible_for_return": true,
    "return_deadline": "2026-05-11"
  }
]
